num_collect/__init__.py
num_collect/py.typed
num_collect/base/__init__.py
num_collect/base/py.typed
num_collect/opt/__init__.py
num_collect/opt/py.typed
num_collect/opt/multi_variate/__init__.py
num_collect/opt/multi_variate/py.typed
num_collect/_cpp_module/__init__.py
num_collect/_cpp_module/py.typed
num_collect/_cpp_module/num_collect_py_cpp_module.cpython-310-x86_64-linux-gnu.so
num_collect/_cpp_module/num_collect_py_cpp_module/py.typed
num_collect/_cpp_module/num_collect_py_cpp_module/__init__.pyi
num_collect/_cpp_module/num_collect_py_cpp_module/opt/py.typed
num_collect/_cpp_module/num_collect_py_cpp_module/opt/__init__.pyi
num_collect/_cpp_module/num_collect_py_cpp_module/opt/multi_variate/py.typed
num_collect/_cpp_module/num_collect_py_cpp_module/opt/multi_variate/__init__.pyi
num_collect/logging/__init__.py
num_collect/logging/py.typed
num_collect/logging/_logger.py
num_collect/logging/_handler.py
numerical_collection_py-0.2.0.dist-info/RECORD
numerical_collection_py-0.2.0.dist-info/METADATA
numerical_collection_py-0.2.0.dist-info/LICENSE.txt
numerical_collection_py-0.2.0.dist-info/WHEEL
numerical_collection_py-0.2.0.dist-info/top_level.txt
